scikit_cycling-0.1.3.dist-info/DESCRIPTION.rst
scikit_cycling-0.1.3.dist-info/METADATA
scikit_cycling-0.1.3.dist-info/RECORD
scikit_cycling-0.1.3.dist-info/WHEEL
scikit_cycling-0.1.3.dist-info/metadata.json
scikit_cycling-0.1.3.dist-info/top_level.txt
skcycling/__init__.py
skcycling/_version.py
skcycling/base.py
skcycling/exceptions.py
skcycling/setup.py
skcycling/__check_build/__init__.py
skcycling/__check_build/_check_build.cp35-win32.pyd
skcycling/__check_build/setup.py
skcycling/datasets/__init__.py
skcycling/datasets/corrupted_data/2013-04-24-22-22-25.fit
skcycling/datasets/corrupted_data/2014-05-17-10-44-53.fit
skcycling/datasets/corrupted_data/2015-11-27-18-54-57.fit
skcycling/datasets/data/2014-05-07-14-26-22.fit
skcycling/datasets/data/2014-05-11-11-39-38.fit
skcycling/datasets/data/2014-07-26-18-50-56.fit
skcycling/datasets/data/rider.csv
skcycling/datasets/tests/__init__.py
skcycling/datasets/tests/test_datasets.py
skcycling/extraction/__init__.py
skcycling/extraction/_power_profile.cp35-win32.pyd
skcycling/extraction/gradient.py
skcycling/extraction/power_profile.py
skcycling/extraction/setup.py
skcycling/io/__init__.py
skcycling/io/base.py
skcycling/io/fit.py
skcycling/io/tests/__init__.py
skcycling/io/tests/test_fit.py
skcycling/metrics/__init__.py
skcycling/metrics/activity.py
skcycling/metrics/power_profile.py
skcycling/metrics/tests/__init__.py
skcycling/metrics/tests/test_activity.py
skcycling/metrics/tests/test_power_profile.py
skcycling/metrics/tests/data/__init__.py
skcycling/metrics/tests/data/rider_power_profile.csv
skcycling/model/__init__.py
skcycling/model/power.py
skcycling/model/tests/__init__.py
skcycling/model/tests/test_power.py
skcycling/tests/__init__.py
skcycling/tests/test_base.py
skcycling/utils/__init__.py
skcycling/utils/validation.py
skcycling/utils/tests/__init__.py
skcycling/utils/tests/test_validation.py
