Metadata-Version: 1.1
Name: scikit-cycling
Version: 0.1.3
Summary: A set of python modules for cyclist using powermeters.
Home-page: https://github.com/scikit-cycling/scikit-cycling
Author: G. Lemaitre
Author-email: g.lemaitre58@gmail.com
License: BSD3
Download-URL: https://github.com/scikit-cycling/scikit-cycling
Platform: UNKNOWN
Classifier: Intended Audience :: Science/Research
Classifier: Intended Audience :: Developers
Classifier: License :: OSI Approved
Classifier: Programming Language :: Python
Classifier: Topic :: Software Development
Classifier: Topic :: Scientific/Engineering
Classifier: Operating System :: Microsoft :: Windows
Classifier: Operating System :: POSIX
Classifier: Operating System :: Unix
Classifier: Operating System :: MacOS
Classifier: Programming Language :: Python :: 2.7
Classifier: Programming Language :: Python :: 3.5
Classifier: Programming Language :: Python :: 3.6
